{"income": {"fiscal_year": ["2019", "2020"], "quarter_count": [4, 4], "latest_quarter": ["Q4", "Q4"], "revenue": [2881, 3781], "cost_of_revenue": [-1485, -1671], "gross_profit": [1394, 2109], "operating_expenses": [-1002, -1121], "selling_general_and_admin": [-813, -917], "research_and_development": [-187, -203], "operating_income": [388, 985], "non_operating_income": [-122, -70], "interest_expense_net": [-122, -71], "pretax_income_adj": [264, 912], "abnormal_gains": [-28, -7], "pretax_income": [235, 904], "income_tax_net": [-7, -176], "income_fr_continuing_ops": [226, 726], "net_extraordinary_gains": [0, 0], "net_income": [226, 726]}, "balance": {"fiscal_year": ["2019", "2020"], "latest_quarter": ["Q4", "Q4"], "shares_basic": [110, 111], "shares_diluted": [111, 112], "cash_and_st_inv": [191, 402], "receivables": [725, 1155], "inventories": [356, 514], "current_assets": [1374, 2238], "ppe_net": [318, 368], "other_lt_assets": [4845, 5353], "non_current_assets": [5164, 5721], "assets": [6538, 7960], "payables": [739, 1271], "st_debt": [9, 380], "current_liabilities": [762, 1652], "lt_debt": [2064, 1609], "non_current_liabilities": [2961, 2572], "liabilities": [3724, 4224], "share_capital": [201, 260], "retained_earnings": [2811, 3507], "equity": [2813, 3735], "liabilities_and_equity": [6538, 7960]}, "cashflow": {"fiscal_year": ["2019", "2020"], "quarter_count": [4, 4], "latest_quarter": ["Q4", "Q4"], "net_income": [226, 726], "depreciation_and_amortization": [212, 244], "non_cash_items": [87, 350], "change_in_working_capital": [-163, -432], "cash_fr_operating": [362, 891], "change_in_ppe_and_intangibles": [-78, -75], "change_in_lt_investment": [-5, -18], "net_cash_fr_acq_disp": [-400, 0], "cash_fr_investing": [-487, -503], "dividends_paid": [-28, -28], "cash_fr_debt_issued": [208, -187], "cash_fr_equity_issued": [14, 30], "cash_fr_financing": [149, -201], "net_change_in_cash": [25, 209]}}